{
  "title": "ModSettings",
  "description": "Modifies the orginal Settings class provided by the user",
  "type": "object",
  "properties": {
    "host": {
      "title": "Host",
      "description": "IP of the host.",
      "default": "127.0.0.1",
      "env_names": [
        "data_portal_ui"
      ],
      "type": "string"
    },
    "port": {
      "title": "Port",
      "description": "Port to expose the server on the specified host",
      "default": 8080,
      "env_names": [
        "data_portal_ui"
      ],
      "type": "integer"
    },
    "svc_search_url": {
      "title": "Metadata Search Service URL",
      "description": "URL for the metadata search service",
      "default": "http://127.0.0.1:8001",
      "env_names": [
        "data_portal_ui"
      ],
      "type": "string"
    },
    "svc_repository_url": {
      "title": "Metadata Repository Service URL",
      "description": "URL for the metadata repository service",
      "default": "http://127.0.0.1:8002",
      "env_names": [
        "data_portal_ui"
      ],
      "type": "string"
    },
    "svc_users_url": {
      "title": "User Database Service URL",
      "description": "URL for the user database service",
      "default": "http://127.0.0.1:8000/api/auth/users",
      "env_names": [
        "data_portal_ui"
      ],
      "type": "string"
    },
    "svc_wps_url": {
      "title": "WPS Service URL",
      "description": "URL for the work package service",
      "default": "http://127.0.0.1:8000/api/wps",
      "env_names": [
        "data_portal_ui"
      ],
      "type": "string"
    }
  },
  "additionalProperties": false
}